<dict>
  <key>main-file</key>
  <string>E:/DeiTCPP/Deit_cpp/solution1/.autopilot/db/ViT.pp.0.cpp</string>
  <key>diagnostics</key>
  <array>
    <dict>
      <key>level</key>
      <string>warning</string>
      <key>filename</key>
      <string>Deit_cpp/src/../include/gmp.h</string>
      <key>line</key>
      <integer>2304</integer>
      <key>column</key>
      <integer>345</integer>
      <key>message</key>
      <string>equality comparison with extraneous parentheses</string>
      <key>ID</key>
      <integer>4827</integer>
      <key>WarningOption</key>
      <string>parentheses-equality</string>
    </dict>
    <dict>
      <key>level</key>
      <string>note</string>
      <key>filename</key>
      <string>Deit_cpp/src/../include/gmp.h</string>
      <key>line</key>
      <integer>2304</integer>
      <key>column</key>
      <integer>345</integer>
      <key>message</key>
      <string>remove extraneous parentheses around the comparison to silence this warning</string>
      <key>ID</key>
      <integer>4186</integer>
    </dict>
    <dict>
      <key>level</key>
      <string>note</string>
      <key>filename</key>
      <string>Deit_cpp/src/../include/gmp.h</string>
      <key>line</key>
      <integer>2304</integer>
      <key>column</key>
      <integer>345</integer>
      <key>message</key>
      <string>use &apos;=&apos; to turn this equality comparison into an assignment</string>
      <key>ID</key>
      <integer>4187</integer>
    </dict>
    <dict>
      <key>level</key>
      <string>warning</string>
      <key>filename</key>
      <string>Deit_cpp/src/ViT.cpp</string>
      <key>line</key>
      <integer>41</integer>
      <key>column</key>
      <integer>9</integer>
      <key>message</key>
      <string>unknown HLS pragma ignored</string>
      <key>ID</key>
      <integer>5572</integer>
      <key>WarningOption</key>
      <string>invalid-hls-pragmas</string>
    </dict>
    <dict>
      <key>level</key>
      <string>warning</string>
      <key>filename</key>
      <string>Deit_cpp/src/ViT.cpp</string>
      <key>line</key>
      <integer>116</integer>
      <key>column</key>
      <integer>62</integer>
      <key>message</key>
      <string>unexpected pragma argument &apos;&lt;&apos;, expects identifier</string>
      <key>ID</key>
      <integer>5555</integer>
      <key>WarningOption</key>
      <string>invalid-hls-pragmas</string>
    </dict>
    <dict>
      <key>level</key>
      <string>warning</string>
      <key>filename</key>
      <string>Deit_cpp/src/ViT.cpp</string>
      <key>line</key>
      <integer>117</integer>
      <key>column</key>
      <integer>62</integer>
      <key>message</key>
      <string>unexpected pragma argument &apos;&lt;&apos;, expects identifier</string>
      <key>ID</key>
      <integer>5555</integer>
      <key>WarningOption</key>
      <string>invalid-hls-pragmas</string>
    </dict>
  </array>
</dict>
